PyMPL-0.5.0.dist-info/WHEEL
PyMPL-0.5.0.dist-info/RECORD
PyMPL-0.5.0.dist-info/top_level.txt
PyMPL-0.5.0.dist-info/DESCRIPTION.rst
PyMPL-0.5.0.dist-info/METADATA
PyMPL-0.5.0.dist-info/metadata.json
pympl/glpkutils.pyc
pympl/solver.py
pympl/glpkutils.py
pympl/__init__.pyc
pympl/pympl.pyc
pympl/__init__.py
pympl/solver.pyc
pympl/pympl.py
pympl/cmds/sosutils.pyc
pympl/cmds/sosutils.py
pympl/cmds/base.pyc
pympl/cmds/sos.pyc
pympl/cmds/xformutils.pyc
pympl/cmds/atsp.pyc
pympl/cmds/xform.py
pympl/cmds/default.py
pympl/cmds/xform.pyc
pympl/cmds/vbp.pyc
pympl/cmds/vbp.py
pympl/cmds/__init__.pyc
pympl/cmds/sos.py
pympl/cmds/__init__.py
pympl/cmds/atsp.py
pympl/cmds/atsputils.py
pympl/cmds/xformutils.py
pympl/cmds/default.pyc
pympl/cmds/atsputils.pyc
pympl/cmds/base.py
pympl/cmds/__pycache__/base.cpython-34.pyc
pympl/cmds/__pycache__/atsputils.cpython-34.pyc
pympl/cmds/__pycache__/sosutils.cpython-34.pyc
pympl/cmds/__pycache__/default.cpython-34.pyc
pympl/cmds/__pycache__/sos.cpython-34.pyc
pympl/cmds/__pycache__/atsp.cpython-34.pyc
pympl/cmds/__pycache__/xform.cpython-34.pyc
pympl/cmds/__pycache__/__init__.cpython-34.pyc
pympl/cmds/__pycache__/vbp.cpython-34.pyc
pympl/cmds/__pycache__/xformutils.cpython-34.pyc
pympl/model/model.pyc
pympl/model/writemod.py
pympl/model/writelp.py
pympl/model/__init__.pyc
pympl/model/writemod.pyc
pympl/model/__init__.py
pympl/model/model.py
pympl/model/writemps.pyc
pympl/model/writelp.pyc
pympl/model/writemps.py
pympl/model/__pycache__/model.cpython-34.pyc
pympl/model/__pycache__/writemps.cpython-34.pyc
pympl/model/__pycache__/writelp.cpython-34.pyc
pympl/model/__pycache__/writemod.cpython-34.pyc
pympl/model/__pycache__/__init__.cpython-34.pyc
pympl/utils/parsing.py
pympl/utils/parsing.pyc
pympl/utils/__init__.pyc
pympl/utils/ampl.py
pympl/utils/ampl.pyc
pympl/utils/__init__.py
pympl/utils/common.pyc
pympl/utils/common.py
pympl/utils/__pycache__/common.cpython-34.pyc
pympl/utils/__pycache__/parsing.cpython-34.pyc
pympl/utils/__pycache__/__init__.cpython-34.pyc
pympl/utils/__pycache__/ampl.cpython-34.pyc
pympl/__pycache__/pympl.cpython-34.pyc
