Metadata-Version: 2.0
Name: PyMPL
Version: 0.5.0
Summary: Mathematical Programming Toolbox for AMPL
Home-page: https://github.com/fdabrandao/pympl
Author: Filipe Brandao
Author-email: fdabrandao@dcc.fc.up.pt
License: GPLv3+
Platform: any
Classifier: Development Status :: 3 - Alpha
Classifier: Intended Audience :: Science/Research
Classifier: Programming Language :: Python
Classifier: Programming Language :: Python :: 3
Classifier: License :: OSI Approved :: GNU General Public License v3 or later (GPLv3+)
Classifier: Topic :: Scientific/Engineering
Requires-Dist: setuptools (>=3.3)
Requires-Dist: future (>=0.15.0)
Requires-Dist: six (>=1.5.2)
